[
  {
      "name": "Fruit Smoothies",
      "shortCode": "FR",
      "pages": {
          "Home": {
              "title": "Fruit Smoothies :: Project Homepage",
              "headerImage": "/static/img/fruits/smoothies.jpeg",
              "subtitle": "Fruit Smoothies - Project Homepage"
          },
          "Rating": {
              "title": "Fruit Smoothies :: Rate the Superheroes",
              "headerImage": "/static/img/fruits/smoothies.jpeg",
              "subtitle": "Rate the smoothies"
          },
          "Leaderboard": {
              "title": "Fruit Smoothies :: Current Leaderboard",
              "headerImage": "/static/img/fruits/smoothies.jpeg",
              "subtitle": "Current Leaderboard - Orange smoothie? Yuck."
          }
      }
  }
]