{
  "$schema": "https://schema.management.azure.com/schemas/2015-01-01/deploymentTemplate.json#",
  "contentVersion": "1.0.0.0",
  "parameters": {
    "HL7FHIRConverter_1_Connection_Name": {
      "type": "string",
      "defaultValue": "HL7FHIRConverter-1"
    },
    "HL7FHIRConverter_1_Connection_DisplayName": {
      "type": "string",
      "defaultValue": "HL7FHIRConverter"
    },
    "HL7FHIRConverter_1_api_key": {
      "type": "securestring",
      "metadata": {
        "description": "The Conversion API Key for this api"
      }
    },
    "azureblob_1_Connection_Name": {
      "type": "string",
      "defaultValue": "hl7blobstorage"
    },
    "azureblob_1_Connection_DisplayName": {
      "type": "string",
      "defaultValue": "hl7blobstorage"
    },
    "azureblob_1_accountName": {
      "type": "string",
      "metadata": {
        "description": "Name of the storage account the connector should use."
      }
      
    },
    "azureblob_1_accessKey": {
      "type": "securestring",
      "metadata": {
        "description": "Specify a valid primary/secondary storage account access key."
      }
    },
    "FHIRServerProxy_1_Connection_Name": {
      "type": "string",
      "defaultValue": "FHIRServerProxy-1"
    },
    "FHIRServerProxy_1_Connection_DisplayName": {
      "type": "string",
      "defaultValue": "FHIR Server"
    },
    "FHIRServerProxy_1_api_key": {
      "type": "securestring",
      "metadata": {
        "description": "The Function Key for this api"
      }
    },
    "servicebus_1_Connection_Name": {
      "type": "string",
      "defaultValue": "HL7ServiceBus"
    },
    "servicebus_1_Connection_DisplayName": {
      "type": "string",
      "defaultValue": "HL7ServiceBus"
    },
    "servicebus_1_connectionString": {
      "type": "securestring",
      "metadata": {
        "description": "Azure Service Bus Connection String"
      }
    },
	 "servicebus_1_queue": {
      "type": "string",
      "metadata": {
        "description": "Azure Service Bus Queue Name"
      }
    },
    "LogicAppLocation": {
      "type": "string",
      "minLength": 1,
      "allowedValues": [
        "[resourceGroup().location]",
        "eastasia",
        "southeastasia",
        "centralus",
        "eastus",
        "eastus2",
        "westus",
        "northcentralus",
        "southcentralus",
        "northeurope",
        "westeurope",
        "japanwest",
        "japaneast",
        "brazilsouth",
        "australiaeast",
        "australiasoutheast",
        "southindia",
        "centralindia",
        "westindia",
        "canadacentral",
        "canadaeast",
        "uksouth",
        "ukwest",
        "westcentralus",
        "westus2",
        "koreacentral",
        "koreasouth",
        "francecentral",
        "francesouth",
        "southafricanorth",
        "southafricawest"
      ],
      "defaultValue": "[resourceGroup().location]"
    },
    "LogicAppName": {
      "type": "string",
      "minLength": 1,
      "defaultValue": "HL7toFHIR"
    }
  },
  "variables": {},
  "resources": [
    {
      "properties": {
        "state": "Enabled",
        "definition": {
          "$schema": "https://schema.management.azure.com/providers/Microsoft.Logic/schemas/2016-06-01/workflowdefinition.json#",
          "actions": {
            "ConvertHL7WithTemplate": {
              "type": "ApiConnection",
              "inputs": {
                "host": {
                  "connection": {
                    "name": "@parameters('$connections')['HL7FHIRConverter']['connectionId']"
                  }
                },
                "method": "post",
                "body": "@{base64ToString(body('Get_blob_content')['$content'])}",
                "headers": {
                  "Content-Type": "text/plain"
                },
                "path": "/api/convert/@{encodeURIComponent(concat('hl7v2/',json(base64ToString(triggerBody()?['ContentData'])).msgtype,'_',json(base64ToString(triggerBody()?['ContentData'])).msgevent,'.hbs'))}"
              },
              "runAfter": {
                "Get_blob_content": [
                  "Succeeded"
                ]
              }
            },
            "Get_blob_content": {
              "type": "ApiConnection",
              "inputs": {
                "host": {
                  "connection": {
                    "name": "@parameters('$connections')['azureblob']['connectionId']"
                  }
                },
                "method": "get",
                "path": "/datasets/default/files/@{encodeURIComponent(encodeURIComponent(concat(json(base64ToString(triggerBody()?['ContentData'])).container,'/',json(base64ToString(triggerBody()?['ContentData'])).filename)))}/content",
                "queries": {
                  "inferContentType": true
                }
              },
              "runAfter": {}
            },
            "Import_Bundle_to_FHIR_Server": {
              "type": "ApiConnection",
              "inputs": {
                "host": {
                  "connection": {
                    "name": "@parameters('$connections')['FHIRServerProxy_1']['connectionId']"
                  }
                },
                "method": "post",
                "body": "@body('ConvertHL7WithTemplate')['fhirResource']",
                "path": "/api/import"
              },
              "runAfter": {
                "ConvertHL7WithTemplate": [
                  "Succeeded"
                ]
              }
            }
          },
          "parameters": {
            "$connections": {
              "defaultValue": {},
              "type": "Object"
            }
          },
          "triggers": {
            "When_a_message_is_received_in_a_queue_(auto-complete)": {
              "type": "ApiConnection",
              "inputs": {
                "host": {
                  "connection": {
                    "name": "@parameters('$connections')['servicebus']['connectionId']"
                  }
                },
                "method": "get",
                "path": "[concat('/@{encodeURIComponent(encodeURIComponent(''',parameters('servicebus_1_queue'),'''))}/messages/head')]",
                "queries": {
                  "queueType": "Main"
                }
              },
              "recurrence": {
                "frequency": "Second",
                "interval": 30
              }
            }
          },
          "contentVersion": "1.0.0.0",
          "outputs": {}
        },
        "parameters": {
          "$connections": {
            "value": {
              "HL7FHIRConverter": {
                "id": "[resourceId('Microsoft.Web/customApis', 'HL7FHIRConverter')]",
                "connectionId": "[resourceId('Microsoft.Web/connections', parameters('HL7FHIRConverter_1_Connection_Name'))]",
                "connectionName": "[parameters('HL7FHIRConverter_1_Connection_Name')]"
              },
              "azureblob": {
                "id": "[concat(subscription().id, '/providers/Microsoft.Web/locations/', parameters('LogicAppLocation'), '/managedApis/', 'azureblob')]",
                "connectionId": "[resourceId('Microsoft.Web/connections', parameters('azureblob_1_Connection_Name'))]",
                "connectionName": "[parameters('azureblob_1_Connection_Name')]"
              },
              "FHIRServerProxy_1": {
                "id": "[resourceId('Microsoft.Web/customApis', 'FHIRServerProxy')]",
                "connectionId": "[resourceId('Microsoft.Web/connections', parameters('FHIRServerProxy_1_Connection_Name'))]",
                "connectionName": "[parameters('FHIRServerProxy_1_Connection_Name')]"
              },
              "servicebus": {
                "id": "[concat(subscription().id, '/providers/Microsoft.Web/locations/', parameters('LogicAppLocation'), '/managedApis/', 'servicebus')]",
                "connectionId": "[resourceId('Microsoft.Web/connections', parameters('servicebus_1_Connection_Name'))]",
                "connectionName": "[parameters('servicebus_1_Connection_Name')]"
              }
            }
          }
        }
      },
      "name": "[parameters('LogicAppName')]",
      "type": "Microsoft.Logic/workflows",
      "location": "[parameters('LogicAppLocation')]",
      "tags": {
        "displayName": "LogicApp"
      },
      "apiVersion": "2016-06-01",
      "dependsOn": [
        "[resourceId('Microsoft.Web/connections', parameters('HL7FHIRConverter_1_Connection_Name'))]",
        "[resourceId('Microsoft.Web/connections', parameters('azureblob_1_Connection_Name'))]",
        "[resourceId('Microsoft.Web/connections', parameters('FHIRServerProxy_1_Connection_Name'))]",
        "[resourceId('Microsoft.Web/connections', parameters('servicebus_1_Connection_Name'))]"
      ]
    },
    {
      "type": "MICROSOFT.WEB/CONNECTIONS",
      "apiVersion": "2018-07-01-preview",
      "name": "[parameters('HL7FHIRConverter_1_Connection_Name')]",
      "location": "[parameters('LogicAppLocation')]",
      "properties": {
        "api": {
          "id": "[resourceId('Microsoft.Web/customApis', 'HL7FHIRConverter')]"
        },
        "displayName": "[parameters('HL7FHIRConverter_1_Connection_DisplayName')]",
        "parameterValues": {
          "api_key": "[parameters('HL7FHIRConverter_1_api_key')]"
        }
      }
    },
    {
      "type": "MICROSOFT.WEB/CONNECTIONS",
      "apiVersion": "2018-07-01-preview",
      "name": "[parameters('azureblob_1_Connection_Name')]",
      "location": "[parameters('LogicAppLocation')]",
      "properties": {
        "api": {
          "id": "[concat(subscription().id, '/providers/Microsoft.Web/locations/', parameters('LogicAppLocation'), '/managedApis/', 'azureblob')]"
        },
        "displayName": "[parameters('azureblob_1_Connection_DisplayName')]",
        "parameterValues": {
          "accountName": "[parameters('azureblob_1_accountName')]",
          "accessKey": "[parameters('azureblob_1_accessKey')]"
        }
      }
    },
    {
      "type": "MICROSOFT.WEB/CONNECTIONS",
      "apiVersion": "2018-07-01-preview",
      "name": "[parameters('FHIRServerProxy_1_Connection_Name')]",
      "location": "[parameters('LogicAppLocation')]",
      "properties": {
        "api": {
          "id": "[resourceId('Microsoft.Web/customApis', 'FHIRServerProxy')]"
        },
        "displayName": "[parameters('FHIRServerProxy_1_Connection_DisplayName')]",
        "parameterValues": {
          "api_key": "[parameters('FHIRServerProxy_1_api_key')]"
        }
      }
    },
    {
      "type": "MICROSOFT.WEB/CONNECTIONS",
      "apiVersion": "2018-07-01-preview",
      "name": "[parameters('servicebus_1_Connection_Name')]",
      "location": "[parameters('LogicAppLocation')]",
      "properties": {
        "api": {
          "id": "[concat(subscription().id, '/providers/Microsoft.Web/locations/', parameters('LogicAppLocation'), '/managedApis/', 'servicebus')]"
        },
        "displayName": "[parameters('servicebus_1_Connection_DisplayName')]",
        "parameterValues": {
          "connectionString": "[parameters('servicebus_1_connectionString')]"
        }
      }
    }
  ],
  "outputs": {}
}