{
    "$schema": "https://schema.management.azure.com/schemas/2015-01-01/deploymentTemplate.json#",
    "contentVersion": "1.0.0.0",
    "parameters": {
      "vnetName": {
        "type": "string",
        "defaultValue": "P20VNet",
        "metadata": {
          "description": "VNet Name"
        }
      },
      "vnetPrefix": {
        "type": "string",
        "defaultValue": "10.0.0.0/16",
        "metadata": {
          "description": "Address Prefix"
        }
      },
      "subnetName": {
        "type": "string",
        "defaultValue": "Default",
        "metadata": {
          "description": "Subnet Name"
        }
      },
      "subnetPrefix": {
        "type": "string",
        "defaultValue": "10.0.0.0/24",
        "metadata": {
          "description": "Subnet Prefix"
        }
      }
    },
    "variables": {
      "defaultNsgName": "defaultNsg"
    },
    "resources": [
      {
        "apiVersion": "2015-06-15",
        "type": "Microsoft.Network/networkSecurityGroups",
        "name": "[variables('defaultNsgName')]",
        "location": "[resourceGroup().location]",
        "properties": {
          "securityRules": [
            {
              "name": "ssh_rule",
              "properties": {
                "description": "Allow SSH",
                "protocol": "Tcp",
                "sourcePortRange": "*",
                "destinationPortRange": "22",
                "sourceAddressPrefix": "Internet",
                "destinationAddressPrefix": "*",
                "access": "Allow",
                "priority": 100,
                "direction": "Inbound"
              }
            },
            {
              "name": "web_rule",
              "properties": {
                "description": "Allow HTTP",
                "protocol": "Tcp",
                "sourcePortRange": "*",
                "destinationPortRange": "80",
                "sourceAddressPrefix": "Internet",
                "destinationAddressPrefix": "*",
                "access": "Allow",
                "priority": 101,
                "direction": "Inbound"
              }
            }
          ]
        }
      },
      {
        "apiVersion": "2015-06-15",
        "type": "Microsoft.Network/virtualNetworks",
        "name": "[parameters('vnetName')]",
        "location": "[resourceGroup().location]",
        "dependsOn": [
          "[concat('Microsoft.Network/networkSecurityGroups/', variables('defaultNsgName'))]"
        ],
        "properties": {
          "addressSpace": {
            "addressPrefixes": [
              "[parameters('vnetPrefix')]"
            ]
          },
          "subnets": [
            {
              "name": "[parameters('subnetName')]",
              "properties": {
                "addressPrefix": "[parameters('subnetPrefix')]",
                "networkSecurityGroup": {
                  "id": "[resourceId('Microsoft.Network/networkSecurityGroups', variables('defaultNsgName'))]"
                }
              }
            }
          ]
        }
      }
    ],
    "outputs": {}
}