{
    "name": "departments_flat",
    "fields": [
      {
        "name": "id",
        "type": "Edm.String",
        "searchable": false,
        "filterable": true,
        "retrievable": true,
        "stored": true,
        "sortable": true,
        "facetable": false,
        "key": true,
        "synonymMaps": []
      },
     {
        "name": "department",
        "type": "Edm.String",
        "searchable": true,
        "filterable": true,
        "retrievable": true,
        "stored": true,
        "sortable": true,
        "facetable": true,
        "key": false,
        "synonymMaps": []
      },
      {
        "name": "description",
        "type": "Edm.String",
        "searchable": true,
        "filterable": false,
        "retrievable": true,
        "stored": true,
        "sortable": false,
        "facetable": false,
        "key": false,
        "synonymMaps": []
      }
    ],
    "scoringProfiles": [],
    "suggesters": [],
    "analyzers": [],
    "normalizers": [],
    "tokenizers": [],
    "tokenFilters": [],
    "charFilters": [],
    "similarity": {
      "@odata.type": "#Microsoft.Azure.Search.BM25Similarity"
    }
  }